yc.py
yc-1.0.dist-info/METADATA
yc-1.0.dist-info/WHEEL
yc-1.0.dist-info/top_level.txt
yc-1.0.dist-info/RECORD
