Metadata-Version: 2.1
Name: yc
Version: 1.0
Summary: first issue
Home-page: http://disanda.github.io
Author: disanda
Author-email: disanda@foxmail.com
License: UNKNOWN
Platform: UNKNOWN
